LICENSE
MANIFEST.in
setup.py
stringformat.py
tests.py
StringFormat.egg-info/PKG-INFO
StringFormat.egg-info/SOURCES.txt
StringFormat.egg-info/dependency_links.txt
StringFormat.egg-info/not-zip-safe
StringFormat.egg-info/top_level.txt